[
  {
    "word": "freeman",
    "translation": "",
    "timestamp": 1762319728820
  },
  {
    "word": "freshen",
    "translation": "",
    "timestamp": 1762319728819
  },
  {
    "word": "French",
    "translation": "",
    "timestamp": 1762319728818
  },
  {
    "word": "F",
    "translation": "",
    "timestamp": 1762319728817
  },
  {
    "word": "fre",
    "translation": "",
    "timestamp": 1762319728816
  },
  {
    "word": "fry",
    "translation": "",
    "timestamp": 1762319728815
  },
  {
    "word": "Freemason",
    "translation": "",
    "timestamp": 1762319728814
  },
  {
    "word": "freemasonry",
    "translation": "",
    "timestamp": 1762319728813
  },
  {
    "word": "fr",
    "translation": "",
    "timestamp": 1762319728812
  },
  {
    "word": "freeness",
    "translation": "",
    "timestamp": 1762319728811
  },
  {
    "word": "freedom",
    "translation": "",
    "timestamp": 1762319728810
  },
  {
    "word": "free",
    "translation": "",
    "timestamp": 1762319728809
  },
  {
    "word": "Frenchify",
    "translation": "",
    "timestamp": 1762319728808
  },
  {
    "word": "fi",
    "translation": "",
    "timestamp": 1762319728807
  },
  {
    "word": "freer",
    "translation": "",
    "timestamp": 1762319728806
  },
  {
    "word": "freesia",
    "translation": "",
    "timestamp": 1762319728805
  },
  {
    "word": "frE",
    "translation": "",
    "timestamp": 1762319728804
  },
  {
    "word": "freo",
    "translation": "",
    "timestamp": 1762319728803
  },
  {
    "word": "frenetic",
    "translation": "",
    "timestamp": 1762319728802
  },
  {
    "word": "fra",
    "translation": "",
    "timestamp": 1762319728801
  },
  {
    "word": "frenzied",
    "translation": "",
    "timestamp": 1762319728800
  },
  {
    "word": "frenum",
    "translation": "",
    "timestamp": 1762319728799
  },
  {
    "word": "frena",
    "translation": "",
    "timestamp": 1762319728798
  },
  {
    "word": "freestonelfre",
    "translation": "",
    "timestamp": 1762319728797
  },
  {
    "word": "frenzy",
    "translation": "",
    "timestamp": 1762319728796
  },
  {
    "word": "freethinker",
    "translation": "",
    "timestamp": 1762319728795
  },
  {
    "word": "frequence",
    "translation": "",
    "timestamp": 1762319728794
  },
  {
    "word": "frequency",
    "translation": "",
    "timestamp": 1762319728793
  },
  {
    "word": "freeway",
    "translation": "",
    "timestamp": 1762319728792
  },
  {
    "word": "freewheel",
    "translation": "",
    "timestamp": 1762319728791
  },
  {
    "word": "frequent",
    "translation": "",
    "timestamp": 1762319728790
  },
  {
    "word": "frikw",
    "translation": "",
    "timestamp": 1762319728789
  },
  {
    "word": "freewill",
    "translation": "",
    "timestamp": 1762319728788
  },
  {
    "word": "frowil",
    "translation": "",
    "timestamp": 1762319728787
  },
  {
    "word": "freeze",
    "translation": "",
    "timestamp": 1762319728786
  },
  {
    "word": "frequentation",
    "translation": "",
    "timestamp": 1762319728785
  },
  {
    "word": "frequentative",
    "translation": "",
    "timestamp": 1762319728784
  },
  {
    "word": "frl",
    "translation": "",
    "timestamp": 1762319728783
  },
  {
    "word": "from",
    "translation": "",
    "timestamp": 1762319728782
  },
  {
    "word": "frecze",
    "translation": "",
    "timestamp": 1762319728781
  },
  {
    "word": "frequently",
    "translation": "",
    "timestamp": 1762319728780
  },
  {
    "word": "freczer",
    "translation": "",
    "timestamp": 1762319728779
  },
  {
    "word": "fresco",
    "translation": "",
    "timestamp": 1762319728778
  },
  {
    "word": "freezing",
    "translation": "",
    "timestamp": 1762319728777
  },
  {
    "word": "freight",
    "translation": "",
    "timestamp": 1762319728776
  },
  {
    "word": "frit",
    "translation": "",
    "timestamp": 1762319728775
  },
  {
    "word": "freightage",
    "translation": "",
    "timestamp": 1762319728774
  },
  {
    "word": "freighter",
    "translation": "",
    "timestamp": 1762319728773
  },
  {
    "word": "fremitus",
    "translation": "",
    "timestamp": 1762319728772
  },
  {
    "word": "Frenchman",
    "translation": "",
    "timestamp": 1762319728771
  },
  {
    "word": "Frenchwoman",
    "translation": "",
    "timestamp": 1762319728770
  },
  {
    "word": "freshly",
    "translation": "",
    "timestamp": 1762319728769
  },
  {
    "word": "freshness",
    "translation": "",
    "timestamp": 1762319728768
  }
]