[
  {
    "word": "diversion",
    "translation": "",
    "timestamp": 1762280153928
  },
  {
    "word": "do",
    "translation": "",
    "timestamp": 1762280153927
  },
  {
    "word": "diversification",
    "translation": "",
    "timestamp": 1762280153926
  },
  {
    "word": "divining",
    "translation": "",
    "timestamp": 1762280153925
  },
  {
    "word": "di",
    "translation": "",
    "timestamp": 1762280153924
  },
  {
    "word": "divinity",
    "translation": "",
    "timestamp": 1762280153923
  },
  {
    "word": "divisibility",
    "translation": "",
    "timestamp": 1762280153922
  },
  {
    "word": "divisible",
    "translation": "",
    "timestamp": 1762280153921
  },
  {
    "word": "diversity",
    "translation": "",
    "timestamp": 1762280153920
  },
  {
    "word": "division",
    "translation": "",
    "timestamp": 1762280153919
  },
  {
    "word": "divert",
    "translation": "",
    "timestamp": 1762280153918
  },
  {
    "word": "DX",
    "translation": "",
    "timestamp": 1762280153917
  },
  {
    "word": "diverticulum",
    "translation": "",
    "timestamp": 1762280153916
  },
  {
    "word": "diverting",
    "translation": "",
    "timestamp": 1762280153915
  },
  {
    "word": "divertissement",
    "translation": "",
    "timestamp": 1762280153914
  },
  {
    "word": "d",
    "translation": "",
    "timestamp": 1762280153913
  },
  {
    "word": "direct",
    "translation": "",
    "timestamp": 1762280153912
  },
  {
    "word": "divest",
    "translation": "",
    "timestamp": 1762280153911
  },
  {
    "word": "divestiture",
    "translation": "",
    "timestamp": 1762280153910
  },
  {
    "word": "divisional",
    "translation": "",
    "timestamp": 1762280153909
  },
  {
    "word": "divestment",
    "translation": "",
    "timestamp": 1762280153908
  },
  {
    "word": "divide",
    "translation": "",
    "timestamp": 1762280153907
  },
  {
    "word": "dIvid",
    "translation": "",
    "timestamp": 1762280153906
  },
  {
    "word": "divisive",
    "translation": "",
    "timestamp": 1762280153905
  },
  {
    "word": "dI",
    "translation": "",
    "timestamp": 1762280153904
  },
  {
    "word": "divisor",
    "translation": "",
    "timestamp": 1762280153903
  },
  {
    "word": "divorce",
    "translation": "",
    "timestamp": 1762280153902
  },
  {
    "word": "divorc",
    "translation": "",
    "timestamp": 1762280153901
  },
  {
    "word": "DS",
    "translation": "",
    "timestamp": 1762280153900
  },
  {
    "word": "divorcee",
    "translation": "",
    "timestamp": 1762280153899
  },
  {
    "word": "divided",
    "translation": "",
    "timestamp": 1762280153898
  },
  {
    "word": "did",
    "translation": "",
    "timestamp": 1762280153897
  },
  {
    "word": "divorcement",
    "translation": "",
    "timestamp": 1762280153896
  },
  {
    "word": "divot",
    "translation": "",
    "timestamp": 1762280153895
  },
  {
    "word": "div",
    "translation": "",
    "timestamp": 1762280153894
  },
  {
    "word": "divulge",
    "translation": "",
    "timestamp": 1762280153893
  },
  {
    "word": "divulgement",
    "translation": "",
    "timestamp": 1762280153892
  },
  {
    "word": "divulgence",
    "translation": "",
    "timestamp": 1762280153891
  },
  {
    "word": "dividend",
    "translation": "",
    "timestamp": 1762280153890
  },
  {
    "word": "divulsion",
    "translation": "",
    "timestamp": 1762280153889
  },
  {
    "word": "Dixie",
    "translation": "",
    "timestamp": 1762280153888
  },
  {
    "word": "dik",
    "translation": "",
    "timestamp": 1762280153887
  },
  {
    "word": "dizziness",
    "translation": "",
    "timestamp": 1762280153886
  },
  {
    "word": "diz",
    "translation": "",
    "timestamp": 1762280153885
  },
  {
    "word": "dizzy",
    "translation": "",
    "timestamp": 1762280153884
  },
  {
    "word": "divider",
    "translation": "",
    "timestamp": 1762280153883
  },
  {
    "word": "dar",
    "translation": "",
    "timestamp": 1762280153882
  },
  {
    "word": "divination",
    "translation": "",
    "timestamp": 1762280153881
  },
  {
    "word": "djinor",
    "translation": "",
    "timestamp": 1762280153880
  },
  {
    "word": "djinnor",
    "translation": "",
    "timestamp": 1762280153879
  },
  {
    "word": "djinni",
    "translation": "",
    "timestamp": 1762280153878
  },
  {
    "word": "DNA",
    "translation": "",
    "timestamp": 1762280153877
  },
  {
    "word": "divine",
    "translation": "",
    "timestamp": 1762280153876
  },
  {
    "word": "deal",
    "translation": "",
    "timestamp": 1762280153875
  },
  {
    "word": "done",
    "translation": "",
    "timestamp": 1762280153874
  },
  {
    "word": "diviner",
    "translation": "",
    "timestamp": 1762280153873
  },
  {
    "word": "diving",
    "translation": "",
    "timestamp": 1762280153872
  },
  {
    "word": "days",
    "translation": "",
    "timestamp": 1762280153871
  },
  {
    "word": "duck",
    "translation": "",
    "timestamp": 1762280153870
  },
  {
    "word": "date",
    "translation": "",
    "timestamp": 1762280153869
  }
]