[
  {
    "word": "stockade",
    "translation": "",
    "timestamp": 1762349140347
  },
  {
    "word": "stomach",
    "translation": "",
    "timestamp": 1762349140346
  },
  {
    "word": "stockpil",
    "translation": "",
    "timestamp": 1762349140345
  },
  {
    "word": "stbk",
    "translation": "",
    "timestamp": 1762349140344
  },
  {
    "word": "stockpot",
    "translation": "",
    "timestamp": 1762349140343
  },
  {
    "word": "StSK",
    "translation": "",
    "timestamp": 1762349140342
  },
  {
    "word": "stock",
    "translation": "",
    "timestamp": 1762349140341
  },
  {
    "word": "shops",
    "translation": "",
    "timestamp": 1762349140340
  },
  {
    "word": "stocktaking",
    "translation": "",
    "timestamp": 1762349140339
  },
  {
    "word": "stocky",
    "translation": "",
    "timestamp": 1762349140338
  },
  {
    "word": "stdK",
    "translation": "",
    "timestamp": 1762349140337
  },
  {
    "word": "stodge",
    "translation": "",
    "timestamp": 1762349140336
  },
  {
    "word": "stdj",
    "translation": "",
    "timestamp": 1762349140335
  },
  {
    "word": "subjectofconvers",
    "translation": "",
    "timestamp": 1762349140334
  },
  {
    "word": "stodgy",
    "translation": "",
    "timestamp": 1762349140333
  },
  {
    "word": "stoic",
    "translation": "",
    "timestamp": 1762349140332
  },
  {
    "word": "SN",
    "translation": "",
    "timestamp": 1762349140331
  },
  {
    "word": "s",
    "translation": "",
    "timestamp": 1762349140330
  },
  {
    "word": "stockbroker",
    "translation": "",
    "timestamp": 1762349140329
  },
  {
    "word": "StOichiometry",
    "translation": "",
    "timestamp": 1762349140328
  },
  {
    "word": "stoiki",
    "translation": "",
    "timestamp": 1762349140327
  },
  {
    "word": "Sm",
    "translation": "",
    "timestamp": 1762349140326
  },
  {
    "word": "Stoicism",
    "translation": "",
    "timestamp": 1762349140325
  },
  {
    "word": "siz",
    "translation": "",
    "timestamp": 1762349140324
  },
  {
    "word": "swoic",
    "translation": "",
    "timestamp": 1762349140323
  },
  {
    "word": "stoke",
    "translation": "",
    "timestamp": 1762349140322
  },
  {
    "word": "stok",
    "translation": "",
    "timestamp": 1762349140321
  },
  {
    "word": "STy",
    "translation": "",
    "timestamp": 1762349140320
  },
  {
    "word": "stokehold",
    "translation": "",
    "timestamp": 1762349140319
  },
  {
    "word": "stokehole",
    "translation": "",
    "timestamp": 1762349140318
  },
  {
    "word": "stoker",
    "translation": "",
    "timestamp": 1762349140317
  },
  {
    "word": "sto",
    "translation": "",
    "timestamp": 1762349140316
  },
  {
    "word": "stole",
    "translation": "",
    "timestamp": 1762349140315
  },
  {
    "word": "stdl",
    "translation": "",
    "timestamp": 1762349140314
  },
  {
    "word": "steal",
    "translation": "",
    "timestamp": 1762349140313
  },
  {
    "word": "S",
    "translation": "",
    "timestamp": 1762349140312
  },
  {
    "word": "stockfish",
    "translation": "",
    "timestamp": 1762349140311
  },
  {
    "word": "stoled",
    "translation": "",
    "timestamp": 1762349140310
  },
  {
    "word": "stold",
    "translation": "",
    "timestamp": 1762349140309
  },
  {
    "word": "stockholder",
    "translation": "",
    "timestamp": 1762349140308
  },
  {
    "word": "stolen",
    "translation": "",
    "timestamp": 1762349140307
  },
  {
    "word": "std",
    "translation": "",
    "timestamp": 1762349140306
  },
  {
    "word": "stockinette",
    "translation": "",
    "timestamp": 1762349140305
  },
  {
    "word": "stockinet",
    "translation": "",
    "timestamp": 1762349140304
  },
  {
    "word": "stolid",
    "translation": "",
    "timestamp": 1762349140303
  },
  {
    "word": "stdI",
    "translation": "",
    "timestamp": 1762349140302
  },
  {
    "word": "stocking",
    "translation": "",
    "timestamp": 1762349140301
  },
  {
    "word": "stolidity",
    "translation": "",
    "timestamp": 1762349140300
  },
  {
    "word": "sta",
    "translation": "",
    "timestamp": 1762349140299
  },
  {
    "word": "stockish",
    "translation": "",
    "timestamp": 1762349140298
  },
  {
    "word": "stoma",
    "translation": "",
    "timestamp": 1762349140297
  },
  {
    "word": "stomataor",
    "translation": "",
    "timestamp": 1762349140296
  },
  {
    "word": "stomas",
    "translation": "",
    "timestamp": 1762349140295
  },
  {
    "word": "ss",
    "translation": "",
    "timestamp": 1762349140294
  },
  {
    "word": "stockjobber",
    "translation": "",
    "timestamp": 1762349140293
  },
  {
    "word": "stolon",
    "translation": "",
    "timestamp": 1762349140292
  },
  {
    "word": "stockman",
    "translation": "",
    "timestamp": 1762349140291
  },
  {
    "word": "stdk",
    "translation": "",
    "timestamp": 1762349140290
  },
  {
    "word": "stim",
    "translation": "",
    "timestamp": 1762349140289
  },
  {
    "word": "system",
    "translation": "",
    "timestamp": 1762349140288
  }
]