[
  {
    "word": "advanced",
    "translation": "",
    "timestamp": 1762268044690
  },
  {
    "word": "aerate",
    "translation": "",
    "timestamp": 1762268044689
  },
  {
    "word": "an",
    "translation": "",
    "timestamp": 1762268044688
  },
  {
    "word": "advertise",
    "translation": "",
    "timestamp": 1762268044687
  },
  {
    "word": "a",
    "translation": "",
    "timestamp": 1762268044686
  },
  {
    "word": "adj",
    "translation": "",
    "timestamp": 1762268044685
  },
  {
    "word": "advertisement",
    "translation": "",
    "timestamp": 1762268044684
  },
  {
    "word": "advertising",
    "translation": "",
    "timestamp": 1762268044683
  },
  {
    "word": "advancement",
    "translation": "",
    "timestamp": 1762268044682
  },
  {
    "word": "advance",
    "translation": "",
    "timestamp": 1762268044681
  },
  {
    "word": "advice",
    "translation": "",
    "timestamp": 1762268044680
  },
  {
    "word": "advantage",
    "translation": "",
    "timestamp": 1762268044679
  },
  {
    "word": "advisable",
    "translation": "",
    "timestamp": 1762268044678
  },
  {
    "word": "advisability",
    "translation": "",
    "timestamp": 1762268044677
  },
  {
    "word": "advise",
    "translation": "",
    "timestamp": 1762268044676
  },
  {
    "word": "advantageous",
    "translation": "",
    "timestamp": 1762268044675
  },
  {
    "word": "advantageously",
    "translation": "",
    "timestamp": 1762268044674
  },
  {
    "word": "adv",
    "translation": "",
    "timestamp": 1762268044673
  },
  {
    "word": "advised",
    "translation": "",
    "timestamp": 1762268044672
  },
  {
    "word": "advection",
    "translation": "",
    "timestamp": 1762268044671
  },
  {
    "word": "advisedly",
    "translation": "",
    "timestamp": 1762268044670
  },
  {
    "word": "advent",
    "translation": "",
    "timestamp": 1762268044669
  },
  {
    "word": "advisement",
    "translation": "",
    "timestamp": 1762268044668
  },
  {
    "word": "adviser",
    "translation": "",
    "timestamp": 1762268044667
  },
  {
    "word": "advisor",
    "translation": "",
    "timestamp": 1762268044666
  },
  {
    "word": "Adventism",
    "translation": "",
    "timestamp": 1762268044665
  },
  {
    "word": "advisory",
    "translation": "",
    "timestamp": 1762268044664
  },
  {
    "word": "advocacy",
    "translation": "",
    "timestamp": 1762268044663
  },
  {
    "word": "advocation",
    "translation": "",
    "timestamp": 1762268044662
  },
  {
    "word": "Adventist",
    "translation": "",
    "timestamp": 1762268044661
  },
  {
    "word": "adventitious",
    "translation": "",
    "timestamp": 1762268044660
  },
  {
    "word": "advocate",
    "translation": "",
    "timestamp": 1762268044659
  },
  {
    "word": "adventive",
    "translation": "",
    "timestamp": 1762268044658
  },
  {
    "word": "adynamia",
    "translation": "",
    "timestamp": 1762268044657
  },
  {
    "word": "adynamic",
    "translation": "",
    "timestamp": 1762268044656
  },
  {
    "word": "adventure",
    "translation": "",
    "timestamp": 1762268044655
  },
  {
    "word": "Al",
    "translation": "",
    "timestamp": 1762268044654
  },
  {
    "word": "adytum",
    "translation": "",
    "timestamp": 1762268044653
  },
  {
    "word": "adyta",
    "translation": "",
    "timestamp": 1762268044652
  },
  {
    "word": "adventurer",
    "translation": "",
    "timestamp": 1762268044651
  },
  {
    "word": "adventuresome",
    "translation": "",
    "timestamp": 1762268044650
  },
  {
    "word": "adventurous",
    "translation": "",
    "timestamp": 1762268044649
  },
  {
    "word": "adz",
    "translation": "",
    "timestamp": 1762268044648
  },
  {
    "word": "adventuress",
    "translation": "",
    "timestamp": 1762268044647
  },
  {
    "word": "aedile",
    "translation": "",
    "timestamp": 1762268044646
  },
  {
    "word": "adverb",
    "translation": "",
    "timestamp": 1762268044645
  },
  {
    "word": "Aegean",
    "translation": "",
    "timestamp": 1762268044644
  },
  {
    "word": "aegis",
    "translation": "",
    "timestamp": 1762268044643
  },
  {
    "word": "adverbial",
    "translation": "",
    "timestamp": 1762268044642
  },
  {
    "word": "ad",
    "translation": "",
    "timestamp": 1762268044641
  },
  {
    "word": "Age",
    "translation": "",
    "timestamp": 1762268044640
  },
  {
    "word": "adversarial",
    "translation": "",
    "timestamp": 1762268044639
  },
  {
    "word": "adversary",
    "translation": "",
    "timestamp": 1762268044638
  },
  {
    "word": "aeolian",
    "translation": "",
    "timestamp": 1762268044637
  },
  {
    "word": "adversative",
    "translation": "",
    "timestamp": 1762268044636
  },
  {
    "word": "adverse",
    "translation": "",
    "timestamp": 1762268044635
  },
  {
    "word": "acolotropic",
    "translation": "",
    "timestamp": 1762268044634
  },
  {
    "word": "anisotropic",
    "translation": "",
    "timestamp": 1762268044633
  },
  {
    "word": "acolian",
    "translation": "",
    "timestamp": 1762268044632
  },
  {
    "word": "adversity",
    "translation": "",
    "timestamp": 1762268044631
  },
  {
    "word": "Acolus",
    "translation": "",
    "timestamp": 1762268044630
  },
  {
    "word": "advert",
    "translation": "",
    "timestamp": 1762268044629
  },
  {
    "word": "acon",
    "translation": "",
    "timestamp": 1762268044628
  },
  {
    "word": "aer",
    "translation": "",
    "timestamp": 1762268044627
  },
  {
    "word": "aero",
    "translation": "",
    "timestamp": 1762268044626
  },
  {
    "word": "advertent",
    "translation": "",
    "timestamp": 1762268044625
  },
  {
    "word": "advertence",
    "translation": "",
    "timestamp": 1762268044624
  },
  {
    "word": "advertency",
    "translation": "",
    "timestamp": 1762268044623
  },
  {
    "word": "arat",
    "translation": "",
    "timestamp": 1762268044622
  },
  {
    "word": "at",
    "translation": "",
    "timestamp": 1762268044621
  },
  {
    "word": "adat",
    "translation": "",
    "timestamp": 1762268044620
  },
  {
    "word": "acar",
    "translation": "",
    "timestamp": 1762268044619
  },
  {
    "word": "alone",
    "translation": "",
    "timestamp": 1762268044618
  }
]