[
  {
    "word": "reunification",
    "translation": "",
    "timestamp": 1762341901958
  },
  {
    "word": "revery",
    "translation": "",
    "timestamp": 1762341901957
  },
  {
    "word": "r",
    "translation": "",
    "timestamp": 1762341901956
  },
  {
    "word": "reverberator",
    "translation": "",
    "timestamp": 1762341901955
  },
  {
    "word": "ri",
    "translation": "",
    "timestamp": 1762341901954
  },
  {
    "word": "reunify",
    "translation": "",
    "timestamp": 1762341901953
  },
  {
    "word": "re",
    "translation": "",
    "timestamp": 1762341901952
  },
  {
    "word": "reunion",
    "translation": "",
    "timestamp": 1762341901951
  },
  {
    "word": "reverberatory",
    "translation": "",
    "timestamp": 1762341901950
  },
  {
    "word": "reunionist",
    "translation": "",
    "timestamp": 1762341901949
  },
  {
    "word": "reunite",
    "translation": "",
    "timestamp": 1762341901948
  },
  {
    "word": "revere",
    "translation": "",
    "timestamp": 1762341901947
  },
  {
    "word": "revers",
    "translation": "",
    "timestamp": 1762341901946
  },
  {
    "word": "reusable",
    "translation": "",
    "timestamp": 1762341901945
  },
  {
    "word": "reverence",
    "translation": "",
    "timestamp": 1762341901944
  },
  {
    "word": "rev",
    "translation": "",
    "timestamp": 1762341901943
  },
  {
    "word": "rdv",
    "translation": "",
    "timestamp": 1762341901942
  },
  {
    "word": "reverend",
    "translation": "",
    "timestamp": 1762341901941
  },
  {
    "word": "revaluate",
    "translation": "",
    "timestamp": 1762341901940
  },
  {
    "word": "revalue",
    "translation": "",
    "timestamp": 1762341901939
  },
  {
    "word": "rEvil",
    "translation": "",
    "timestamp": 1762341901938
  },
  {
    "word": "reverent",
    "translation": "",
    "timestamp": 1762341901937
  },
  {
    "word": "reverential",
    "translation": "",
    "timestamp": 1762341901936
  },
  {
    "word": "revamp",
    "translation": "",
    "timestamp": 1762341901935
  },
  {
    "word": "reverie",
    "translation": "",
    "timestamp": 1762341901934
  },
  {
    "word": "ravir",
    "translation": "",
    "timestamp": 1762341901933
  },
  {
    "word": "revanche",
    "translation": "",
    "timestamp": 1762341901932
  },
  {
    "word": "ra",
    "translation": "",
    "timestamp": 1762341901931
  },
  {
    "word": "reversal",
    "translation": "",
    "timestamp": 1762341901930
  },
  {
    "word": "reveal",
    "translation": "",
    "timestamp": 1762341901929
  },
  {
    "word": "reverse",
    "translation": "",
    "timestamp": 1762341901928
  },
  {
    "word": "rl",
    "translation": "",
    "timestamp": 1762341901927
  },
  {
    "word": "revealer",
    "translation": "",
    "timestamp": 1762341901926
  },
  {
    "word": "reveille",
    "translation": "",
    "timestamp": 1762341901925
  },
  {
    "word": "revel",
    "translation": "",
    "timestamp": 1762341901924
  },
  {
    "word": "revelous",
    "translation": "",
    "timestamp": 1762341901923
  },
  {
    "word": "reveler",
    "translation": "",
    "timestamp": 1762341901922
  },
  {
    "word": "reveller",
    "translation": "",
    "timestamp": 1762341901921
  },
  {
    "word": "revelation",
    "translation": "",
    "timestamp": 1762341901920
  },
  {
    "word": "reversibility",
    "translation": "",
    "timestamp": 1762341901919
  },
  {
    "word": "revelator",
    "translation": "",
    "timestamp": 1762341901918
  },
  {
    "word": "revelatory",
    "translation": "",
    "timestamp": 1762341901917
  },
  {
    "word": "revelry",
    "translation": "",
    "timestamp": 1762341901916
  },
  {
    "word": "revenant",
    "translation": "",
    "timestamp": 1762341901915
  },
  {
    "word": "reversible",
    "translation": "",
    "timestamp": 1762341901914
  },
  {
    "word": "reaction",
    "translation": "",
    "timestamp": 1762341901913
  },
  {
    "word": "revenge",
    "translation": "",
    "timestamp": 1762341901912
  },
  {
    "word": "reversion",
    "translation": "",
    "timestamp": 1762341901911
  },
  {
    "word": "revengeful",
    "translation": "",
    "timestamp": 1762341901910
  },
  {
    "word": "revenue",
    "translation": "",
    "timestamp": 1762341901909
  },
  {
    "word": "reverberant",
    "translation": "",
    "timestamp": 1762341901908
  },
  {
    "word": "reversioner",
    "translation": "",
    "timestamp": 1762341901907
  },
  {
    "word": "reverberate",
    "translation": "",
    "timestamp": 1762341901906
  },
  {
    "word": "revert",
    "translation": "",
    "timestamp": 1762341901905
  },
  {
    "word": "reverberation",
    "translation": "",
    "timestamp": 1762341901904
  },
  {
    "word": "reverberative",
    "translation": "",
    "timestamp": 1762341901903
  },
  {
    "word": "rit",
    "translation": "",
    "timestamp": 1762341901902
  }
]