[
  {
    "word": "comedian",
    "translation": "",
    "timestamp": 1762287584810
  },
  {
    "word": "commensurate",
    "translation": "",
    "timestamp": 1762287584809
  },
  {
    "word": "comedic",
    "translation": "",
    "timestamp": 1762287584808
  },
  {
    "word": "comedienne",
    "translation": "",
    "timestamp": 1762287584807
  },
  {
    "word": "comedo",
    "translation": "",
    "timestamp": 1762287584806
  },
  {
    "word": "comedown",
    "translation": "",
    "timestamp": 1762287584805
  },
  {
    "word": "comedy",
    "translation": "",
    "timestamp": 1762287584804
  },
  {
    "word": "come",
    "translation": "",
    "timestamp": 1762287584803
  },
  {
    "word": "commandant",
    "translation": "",
    "timestamp": 1762287584802
  },
  {
    "word": "comely",
    "translation": "",
    "timestamp": 1762287584801
  },
  {
    "word": "comeliness",
    "translation": "",
    "timestamp": 1762287584800
  },
  {
    "word": "commandeer",
    "translation": "",
    "timestamp": 1762287584799
  },
  {
    "word": "c",
    "translation": "",
    "timestamp": 1762287584798
  },
  {
    "word": "commander",
    "translation": "",
    "timestamp": 1762287584797
  },
  {
    "word": "comer",
    "translation": "",
    "timestamp": 1762287584796
  },
  {
    "word": "chief",
    "translation": "",
    "timestamp": 1762287584795
  },
  {
    "word": "comestible",
    "translation": "",
    "timestamp": 1762287584794
  },
  {
    "word": "commandery",
    "translation": "",
    "timestamp": 1762287584793
  },
  {
    "word": "comet",
    "translation": "",
    "timestamp": 1762287584792
  },
  {
    "word": "commanding",
    "translation": "",
    "timestamp": 1762287584791
  },
  {
    "word": "comeuppance",
    "translation": "",
    "timestamp": 1762287584790
  },
  {
    "word": "comfit",
    "translation": "",
    "timestamp": 1762287584789
  },
  {
    "word": "commandment",
    "translation": "",
    "timestamp": 1762287584788
  },
  {
    "word": "comfort",
    "translation": "",
    "timestamp": 1762287584787
  },
  {
    "word": "commando",
    "translation": "",
    "timestamp": 1762287584786
  },
  {
    "word": "comfortable",
    "translation": "",
    "timestamp": 1762287584785
  },
  {
    "word": "command",
    "translation": "",
    "timestamp": 1762287584784
  },
  {
    "word": "comfortableness",
    "translation": "",
    "timestamp": 1762287584783
  },
  {
    "word": "comfortably",
    "translation": "",
    "timestamp": 1762287584782
  },
  {
    "word": "commeasurable",
    "translation": "",
    "timestamp": 1762287584781
  },
  {
    "word": "comforter",
    "translation": "",
    "timestamp": 1762287584780
  },
  {
    "word": "comme",
    "translation": "",
    "timestamp": 1762287584779
  },
  {
    "word": "commemorate",
    "translation": "",
    "timestamp": 1762287584778
  },
  {
    "word": "comfortless",
    "translation": "",
    "timestamp": 1762287584777
  },
  {
    "word": "commemoration",
    "translation": "",
    "timestamp": 1762287584776
  },
  {
    "word": "comfrey",
    "translation": "",
    "timestamp": 1762287584775
  },
  {
    "word": "commemorative",
    "translation": "",
    "timestamp": 1762287584774
  },
  {
    "word": "comfy",
    "translation": "",
    "timestamp": 1762287584773
  },
  {
    "word": "commemoratory",
    "translation": "",
    "timestamp": 1762287584772
  },
  {
    "word": "comic",
    "translation": "",
    "timestamp": 1762287584771
  },
  {
    "word": "commence",
    "translation": "",
    "timestamp": 1762287584770
  },
  {
    "word": "commencement",
    "translation": "",
    "timestamp": 1762287584769
  },
  {
    "word": "commend",
    "translation": "",
    "timestamp": 1762287584768
  },
  {
    "word": "commendable",
    "translation": "",
    "timestamp": 1762287584767
  },
  {
    "word": "coming",
    "translation": "",
    "timestamp": 1762287584766
  },
  {
    "word": "commendation",
    "translation": "",
    "timestamp": 1762287584765
  },
  {
    "word": "comitia",
    "translation": "",
    "timestamp": 1762287584764
  },
  {
    "word": "commendatory",
    "translation": "",
    "timestamp": 1762287584763
  },
  {
    "word": "commensal",
    "translation": "",
    "timestamp": 1762287584762
  },
  {
    "word": "comity",
    "translation": "",
    "timestamp": 1762287584761
  },
  {
    "word": "commensalismicommensality",
    "translation": "",
    "timestamp": 1762287584760
  },
  {
    "word": "comma",
    "translation": "",
    "timestamp": 1762287584759
  },
  {
    "word": "commensurable",
    "translation": "",
    "timestamp": 1762287584758
  },
  {
    "word": "care",
    "translation": "",
    "timestamp": 1762287584757
  },
  {
    "word": "circus",
    "translation": "",
    "timestamp": 1762287584756
  }
]